ratelimitqueue/__init__.py
ratelimitqueue/exceptions.py
ratelimitqueue/ratelimitqueue.py
ratelimitqueue/utils.py
ratelimitqueue-0.2.0.dist-info/METADATA
ratelimitqueue-0.2.0.dist-info/RECORD
ratelimitqueue-0.2.0.dist-info/WHEEL
ratelimitqueue-0.2.0.dist-info/top_level.txt
