Metadata-Version: 2.1
Name: ratelimitqueue
Version: 0.2.0
Summary: A thread safe, rate limited queue.
Home-page: https://www.github.com/JohnPaton/ratelimitqueue
Author: John Paton
Author-email: john@johnpaton.net
License: UNKNOWN
Platform: UNKNOWN
Classifier: Programming Language :: Python :: 3
Classifier: Programming Language :: Python :: 3.4
Classifier: Programming Language :: Python :: 3.5
Classifier: Programming Language :: Python :: 3.6
Classifier: Programming Language :: Python :: 3.7
Classifier: Development Status :: 4 - Beta
Classifier: License :: Freely Distributable
Classifier: License :: OSI Approved :: MIT License
Classifier: Operating System :: OS Independent
Classifier: Topic :: Internet
Requires-Python: >=3.4
